Metadata-Version: 2.1
Name: lifeproof
Version: 0.0.1
Summary: Create proofs of life to detect when a program fails.
Home-page: https://github.com/jmgomezsoriano/lifeproof
Author: José Manuel Gómez Soriano
Author-email: jmgomez.soriano@gmail.com
License: lGPLv3
Platform: UNKNOWN
Classifier: Programming Language :: Python :: 3
Classifier: License :: OSI Approved :: GNU General Public License v3 (GPLv3)
Classifier: Operating System :: OS Independent
Requires-Python: >=3.7
